setup.py
obpy/__init__.py
obpy/config.py
obpy/obpy.py
obpy/util.py
obpy.egg-info/PKG-INFO
obpy.egg-info/SOURCES.txt
obpy.egg-info/dependency_links.txt
obpy.egg-info/not-zip-safe
obpy.egg-info/requires.txt
obpy.egg-info/top_level.txt
tests/__init__.py
tests/test_lib.py
tests/test_util.py