Metadata-Version: 1.1
Name: obpy
Version: 0.0.1
Summary: OpenBikes API library
Home-page: https://github.com/OpenBikes/obpy/
Author: Axel Bellec
Author-email: contact.openbikes@gmail.com
License: MIT
Download-URL: https://github.com/openbikes/obpy/archive/1.0.0.tar.gz
Keywords: openbikes api client sdk
Platform: any
Classifier: Programming Language :: Python :: 3
Classifier: Programming Language :: Python :: 3.3
Classifier: Programming Language :: Python :: 3.4
Classifier: Programming Language :: Python :: 3.5
Classifier: Intended Audience :: Developers
Classifier: License :: OSI Approved :: MIT License
